AUTHORS.rst
LICENSE
MANIFEST.in
README.rst
setup.py
etcdfs/__init__.py
etcdfs/etcdfs.py
etcdfs.egg-info/PKG-INFO
etcdfs.egg-info/SOURCES.txt
etcdfs.egg-info/dependency_links.txt
etcdfs.egg-info/entry_points.txt
etcdfs.egg-info/not-zip-safe
etcdfs.egg-info/requires.txt
etcdfs.egg-info/top_level.txt
tests/__init__.py