Metadata-Version: 1.1
Name: etcdfs
Version: 0.1.0
Summary: Filesystem based on etcd
Home-page: https://github.com/cstavr/etcdfs
Author: Christos Stavrakakis
Author-email: stavr.chris@gmail.com
License: BSD license
Keywords: etcdfs
Platform: UNKNOWN
Classifier: License :: OSI Approved :: BSD License
Classifier: Programming Language :: Python :: 2
Classifier: Programming Language :: Python :: 2.7
